{
	"info": {
		"_postman_id": "d892d11b-5b26-4471-9213-1957f9da39af",
		"name": "backend_feb",
		"schema": "https://schema.getpostman.com/json/collection/v2.0.0/collection.json",
		"_exporter_id": "3112594"
	},
	"item": [
		{
			"name": "GET_METHOD",
			"request": {
				"method": "GET",
				"header": [],
				"url": "http://localhost:8080"
			},
			"response": []
		},
		{
			"name": "POST_METHOD",
			"request": {
				"method": "POST",
				"header": [],
				"body": {
					"mode": "raw",
					"raw": "{\n    \"name\":\"akash\",\n    \"age\":33\n}",
					"options": {
						"raw": {
							"language": "json"
						}
					}
				},
				"url": "http://localhost:8080"
			},
			"response": []
		}
	]
}